LinuxMinglingxingYuShellJiaobenJiaocheng/README.md
LinuxMinglingxingYuShellJiaobenJiaocheng/__init__.py
LinuxMinglingxingYuShellJiaobenJiaocheng/__main__.py
LinuxMinglingxingYuShellJiaobenJiaocheng/file.epub
LinuxMinglingxingYuShellJiaobenJiaocheng/index.html
LinuxMinglingxingYuShellJiaobenJiaocheng/css/__init__.py
LinuxMinglingxingYuShellJiaobenJiaocheng/css/annotations.css
LinuxMinglingxingYuShellJiaobenJiaocheng/css/main.css
LinuxMinglingxingYuShellJiaobenJiaocheng/css/normalize.css
LinuxMinglingxingYuShellJiaobenJiaocheng/css/popup.css
LinuxMinglingxingYuShellJiaobenJiaocheng/font/__init__.py
LinuxMinglingxingYuShellJiaobenJiaocheng/font/fontello.eot
LinuxMinglingxingYuShellJiaobenJiaocheng/font/fontello.svg
LinuxMinglingxingYuShellJiaobenJiaocheng/font/fontello.ttf
LinuxMinglingxingYuShellJiaobenJiaocheng/font/fontello.woff
LinuxMinglingxingYuShellJiaobenJiaocheng/img/__init__.py
LinuxMinglingxingYuShellJiaobenJiaocheng/img/annotator-glyph-sprite.png
LinuxMinglingxingYuShellJiaobenJiaocheng/img/annotator-icon-sprite.png
LinuxMinglingxingYuShellJiaobenJiaocheng/img/apple-touch-icon.png
LinuxMinglingxingYuShellJiaobenJiaocheng/img/cancelfullscreen.png
LinuxMinglingxingYuShellJiaobenJiaocheng/img/close.png
LinuxMinglingxingYuShellJiaobenJiaocheng/img/fullscreen.png
LinuxMinglingxingYuShellJiaobenJiaocheng/img/loader.gif
LinuxMinglingxingYuShellJiaobenJiaocheng/img/menu-icon.png
LinuxMinglingxingYuShellJiaobenJiaocheng/img/save.png
LinuxMinglingxingYuShellJiaobenJiaocheng/img/saved.png
LinuxMinglingxingYuShellJiaobenJiaocheng/img/settings-s.png
LinuxMinglingxingYuShellJiaobenJiaocheng/img/settings.png
LinuxMinglingxingYuShellJiaobenJiaocheng/img/star.png
LinuxMinglingxingYuShellJiaobenJiaocheng/js/__init__.py
LinuxMinglingxingYuShellJiaobenJiaocheng/js/epub.js
LinuxMinglingxingYuShellJiaobenJiaocheng/js/epub.min.js
LinuxMinglingxingYuShellJiaobenJiaocheng/js/epub.min.map
LinuxMinglingxingYuShellJiaobenJiaocheng/js/hooks.min.js
linux_minglingxing_yu_shell_jiaoben_jiaocheng-2024.3.6.0.dist-info/METADATA
linux_minglingxing_yu_shell_jiaoben_jiaocheng-2024.3.6.0.dist-info/WHEEL
linux_minglingxing_yu_shell_jiaoben_jiaocheng-2024.3.6.0.dist-info/entry_points.txt
linux_minglingxing_yu_shell_jiaoben_jiaocheng-2024.3.6.0.dist-info/top_level.txt
linux_minglingxing_yu_shell_jiaoben_jiaocheng-2024.3.6.0.dist-info/RECORD
